kolibri_oidc_provider_plugin/__init__.py
kolibri_oidc_provider_plugin/kolibri_plugin.py
kolibri_oidc_provider_plugin/options.py
kolibri_oidc_provider_plugin/root_urls.py
kolibri_oidc_provider_plugin/settings.py
kolibri_oidc_provider_plugin/management/__init__.py
kolibri_oidc_provider_plugin/management/commands/__init__.py
kolibri_oidc_provider_plugin/management/commands/oidccreateclient.py
kolibri_oidc_provider_plugin/templates/oidc_provider/authorize.html
kolibri_oidc_provider_plugin/templates/oidc_provider/authorize_without_consent.html
kolibri_oidc_provider_plugin/templates/oidc_provider/error.html
kolibri_oidc_provider_plugin-0.0.4.dist-info/AUTHORS.rst
kolibri_oidc_provider_plugin-0.0.4.dist-info/LICENSE
kolibri_oidc_provider_plugin-0.0.4.dist-info/METADATA
kolibri_oidc_provider_plugin-0.0.4.dist-info/WHEEL
kolibri_oidc_provider_plugin-0.0.4.dist-info/entry_points.txt
kolibri_oidc_provider_plugin-0.0.4.dist-info/top_level.txt
kolibri_oidc_provider_plugin-0.0.4.dist-info/RECORD
